<annotation>
	<folder>annotazioni</folder>
	<filename>EG_-_CS_#003_014.jpg</filename>
	<path>../image/EG_-_CS_#003_014.jpg</path>
	<source>
		<database>Unknown</database>
	</source>
	<size>
		<width>1280</width>
		<height>1977</height>
		<depth>3</depth>
	</size>
	<segmented>0</segmented>
	<object>
		<name>Vignetta</name>
		<pose>Unspecified</pose>
		<truncated>1</truncated>
		<difficult>0</difficult>
		<bndbox>
			<xmin>1</xmin>
			<ymin>5</ymin>
			<xmax>1275</xmax>
			<ymax>449</ymax>
		</bndbox>
	</object>
	<object>
		<name>Vignetta</name>
		<pose>Unspecified</pose>
		<truncated>1</truncated>
		<difficult>0</difficult>
		<bndbox>
			<xmin>2</xmin>
			<ymin>461</ymin>
			<xmax>1280</xmax>
			<ymax>843</ymax>
		</bndbox>
	</object>
	<object>
		<name>Vignetta</name>
		<pose>Unspecified</pose>
		<truncated>1</truncated>
		<difficult>0</difficult>
		<bndbox>
			<xmin>1</xmin>
			<ymin>806</ymin>
			<xmax>1278</xmax>
			<ymax>1358</ymax>
		</bndbox>
	</object>
	<object>
		<name>Vignetta</name>
		<pose>Unspecified</pose>
		<truncated>1</truncated>
		<difficult>0</difficult>
		<bndbox>
			<xmin>1</xmin>
			<ymin>1173</ymin>
			<xmax>1275</xmax>
			<ymax>1635</ymax>
		</bndbox>
	</object>
	<object>
		<name>Vignetta</name>
		<pose>Unspecified</pose>
		<truncated>1</truncated>
		<difficult>0</difficult>
		<bndbox>
			<xmin>2</xmin>
			<ymin>1533</ymin>
			<xmax>1278</xmax>
			<ymax>1977</ymax>
		</bndbox>
	</object>
	<object>
		<name>Baloon</name>
		<pose>Unspecified</pose>
		<truncated>0</truncated>
		<difficult>0</difficult>
		<bndbox>
			<xmin>811</xmin>
			<ymin>33</ymin>
			<xmax>1208</xmax>
			<ymax>233</ymax>
		</bndbox>
	</object>
	<object>
		<name>Baloon</name>
		<pose>Unspecified</pose>
		<truncated>0</truncated>
		<difficult>0</difficult>
		<bndbox>
			<xmin>887</xmin>
			<ymin>1030</ymin>
			<xmax>1069</xmax>
			<ymax>1179</ymax>
		</bndbox>
	</object>
	<object>
		<name>Baloon</name>
		<pose>Unspecified</pose>
		<truncated>0</truncated>
		<difficult>0</difficult>
		<bndbox>
			<xmin>196</xmin>
			<ymin>1406</ymin>
			<xmax>429</xmax>
			<ymax>1506</ymax>
		</bndbox>
	</object>
	<object>
		<name>Baloon</name>
		<pose>Unspecified</pose>
		<truncated>1</truncated>
		<difficult>0</difficult>
		<bndbox>
			<xmin>1123</xmin>
			<ymin>1767</ymin>
			<xmax>1280</xmax>
			<ymax>1952</ymax>
		</bndbox>
	</object>
</annotation>
